{
    "required": ["plaintext"]
    "properties": {
        "ssn": {
            "encrypt": {
                "keyId": [
                    {
                        "$binary": {
                            "base64": "SRXmiJF1S6C15mam8N/O2g==",
                            "subType": "04"
                        }
                    }
                ],
                "bsonType": "string",
                "algorithm": "AEAD_AES_256_CBC_HMAC_SHA_512-Deterministic"
            }
        },
	"palintext": {
	  bsonType : "string"
	}
    },
    "bsonType": "object"
}
